{"guide_node相关_概要.md":"ab52bbcf","guide_react_react中的事件机制.md":"678d4b07","guide_canvas_通过上下分层优化canvas书写性能.md":"c74acd54","guide_javascript相关_事件循环机制.md":"89d9e025","guide_javascript相关_定义.md":"201cc090","guide_javascript相关_对象常见的api.md":"bc6f7046","guide_javascript相关_基础概念.md":"376bbba7","guide_javascript相关_字符串常见的api.md":"d6d619a0","guide_react_react与vue的区别.md":"dd91392f","guide_react_react为什么要使用jsx.md":"653ea580","guide_react_react是如何渲染的.md":"cfc3f75d","guide_react_react是什么.md":"47027d8c","guide_redux_源码解读.md":"1bcebe3b","guide_react_diff算法.md":"15a72268","guide_react_react异常机制.md":"5e83ab41","guide_react_react组件是如何通信的.md":"da296874","guide_javascript相关_javascript执行机制.md":"43ede40b","guide_react_react中的异常机制.md":"0a1ab7ed","guide_canvas_canvas尺寸及分辨率矫正.md":"6c730630","guide_javascript相关_js异常捕获机制.md":"4ba30946","guide_javascript相关_javascript编译机制.md":"c5453993","guide_canvas_如何在canvas画板上自由书写.md":"85b688ac","guide_浏览器相关_浏览器进程架构.md":"cadc5108","guide_javascript相关_新的运算符.md":"43ffbc43","guide_javascript相关_正则表达式.md":"0a21bca5","guide_javascript相关_es6相关.md":"bb3a506a","guide_javascript相关_数据类型.md":"baa0b1ee","guide_javascript相关_数组常见的api.md":"a42d39f4","guide_webpack_index.md":"80f0f240","guide_javascript相关_继承相关.md":"a7964812","guide_浏览器相关_概要.md":"3c06f277","guide_浏览器相关_浏览器渲染流程.md":"29240533","guide_浏览器相关_浏览器内核.md":"442b032e","guide_浏览器相关_浏览器安全.md":"9c4dcc7f","guide_canvas_通过 offscreencanvas _ worker 提高书写性能.md":"d4b8355f","guide_浏览器相关_浏览器缓存.md":"60cc8b24","guide_网络相关_常见的问题.md":"12df8217","guide_网络相关_cdn.md":"2bcb0d4f","guide_webpack_构建流程.md":"507f33f3","guide_网络相关_http.md":"33be4e2e","guide_网络相关_https.md":"37ad460c","guide_网络相关_响应报文.md":"7c9a11b5","guide_javascript相关_promise.md":"348f24bc","guide_网络相关_请求报文.md":"7cd40533","guide_网络相关_概要.md":"60c649b5","guide_网络相关_跨域请求.md":"7db9ab65","guide_javascript相关_dom相关.md":"b2444ec8","index.md":"c07f5067","guide_canvas_通过贝塞尔曲线优化canvas书写性能.md":"7e3a42f3","guide_css相关_position.md":"c46d25b7","guide_css相关_display.md":"e137a156","guide_react_什么是fiber.md":"f730fe95","guide_redux_设计理念.md":"a1686bdf","guide_canvas_可视区域内渲染提高canvas书写性能.md":"b9033982","guide_css相关_概要.md":"06bb844c","guide_javascript相关_index.md":"6c2e2a6e","guide_react_react中的性能优化.md":"85626bb3","guide_canvas_通过离屏渲染提高canvas书写性能.md":"8c62e943","guide_react_setstate是同步还是异步的.md":"49e99f9d","guide_网络相关_dns.md":"1eed005b","guide_javascript相关_垃圾回收机制.md":"199c6ef2","guide_网络相关_get请求和post请求的区别.md":"f8ae7be1","guide_react_如何设计react组件.md":"5294ecbc","guide_react_常见的问题.md":"48a55181"}
